odoo/addons/web_theme_classic/README.rst
odoo/addons/web_theme_classic/__init__.py
odoo/addons/web_theme_classic/__manifest__.py
odoo/addons/web_theme_classic/i18n/it.po
odoo/addons/web_theme_classic/i18n/web_theme_classic.pot
odoo/addons/web_theme_classic/readme/CONTRIBUTORS.md
odoo/addons/web_theme_classic/readme/DESCRIPTION.md
odoo/addons/web_theme_classic/static/description/icon.png
odoo/addons/web_theme_classic/static/description/index.html
odoo/addons/web_theme_classic/static/description/product_template_form_with_module.png
odoo/addons/web_theme_classic/static/description/product_template_form_without_module.png
odoo/addons/web_theme_classic/static/src/scss/web_theme_classic.scss
odoo_addon_web_theme_classic-18.0.1.0.0.2.dist-info/METADATA
odoo_addon_web_theme_classic-18.0.1.0.0.2.dist-info/WHEEL
odoo_addon_web_theme_classic-18.0.1.0.0.2.dist-info/top_level.txt
odoo_addon_web_theme_classic-18.0.1.0.0.2.dist-info/RECORD
